prasys/__init__.py
prasys/data.py
prasys/metrics.py
prasys/plots.py
prasys-0.2.3.dist-info/LICENSE
prasys-0.2.3.dist-info/METADATA
prasys-0.2.3.dist-info/WHEEL
prasys-0.2.3.dist-info/top_level.txt
prasys-0.2.3.dist-info/RECORD
